MANIFEST.in
setup.py
api/bme680.c
api/bme680.h
api/bme680_defs.h
api/bme680_funcs.c
melopero_bme680/BME680.py
melopero_bme680/__init__.py
melopero_bme680.egg-info/PKG-INFO
melopero_bme680.egg-info/SOURCES.txt
melopero_bme680.egg-info/dependency_links.txt
melopero_bme680.egg-info/top_level.txt